nlp_toolbox/__init__.py
nlp_toolbox/ebook.py
nlp_toolbox/gpt_model.py
nlp_toolbox/markdown.py
nlp_toolbox/ocr.py
nlp_toolbox/text_preprocessing.py
nlp_toolbox/utils.py
nlp_toolbox/web2text.py
nlp_toolbox/wordcloud.py
nlp_toolbox-0.0.3.dist-info/LICENSE
nlp_toolbox-0.0.3.dist-info/METADATA
nlp_toolbox-0.0.3.dist-info/WHEEL
nlp_toolbox-0.0.3.dist-info/top_level.txt
nlp_toolbox-0.0.3.dist-info/RECORD
