Metadata-Version: 2.1
Name: nlp-toolbox
Version: 0.0.3
Summary: Natural Language Processing Tools
Home-page: https://github.com/thinh-vu/nlp_toolbox
Author: Thinh Vu
Author-email: mrthinh@live.com
Classifier: Programming Language :: Python :: 3
Classifier: License :: OSI Approved :: MIT License
Classifier: Operating System :: OS Independent
Requires-Python: >=3.7
License-File: LICENSE
Requires-Dist: poetry-core
Requires-Dist: trafilatura
Requires-Dist: newspaper3k
Requires-Dist: nltk
Requires-Dist: wordcloud
Requires-Dist: spacy
Requires-Dist: ebooklib
Requires-Dist: ur-gadget
Requires-Dist: pytesseract
